<!DOCTYPE beans PUBLIC "-//SPRING//DTD BEAN//EN" "http://www.springframework.org/dtd/spring-beans.dtd">
<beans>
	<bean id="ExportAccount"
	class="com.salesforce.dataloader.process.ProcessRunner"
	singleton="false">
	<description>Update Status from Users</description>
	<property name="name" value="UpdateUserStatus"/>
	<property name="configOverrideMap">
		<map>
		
			<entry key="sfdc.debugMessages" value="false"/>
			<entry key="sfdc.debugMessagesFile" value="C:\Program Files (x86)\Jenkins\jobs\Jenkins Git Test"/>
			
			<entry key="sfdc.endpoint" value="https://login.salesforce.com"/>
			<entry key="sfdc.username" value="sampathtechm.sfdc@gmail.com"/>
			<entry key="sfdc.password" value="18d2dbb76f82cf30be9b56dcf30a44f3"/>
			<entry key="process.encryptionKeyFile" value="C:\Users\swainr2\AppData\Local\salesforce.com\Data Loader\key\Global.key"/> 
			
			<entry key="sfdc.timeoutSecs" value="600"/>
			<entry key="sfdc.loadBatchSize" value="200"/>
			<entry key="sfdc.useBulkApi" value="true"/>
			<entry key="sfdc.entity" value="account"/>		
			
			<entry key="process.operation" value="Extract"/>
			<entry key="process.mappingFile" value="C:\Program Files (x86)\Jenkins\workspace\Jenkins Git Test\Dataloader\account.sdl"/>
			<entry key="process.outputSuccess" value="C:\Program Files (x86)\Jenkins\jobs\Jenkins Git Test" /> 
			<entry key="process.outputError" value="C:\Program Files (x86)\Jenkins\jobs\Jenkins Git Test" /> 
			<entry key="process.initialLastRunDate" value="2017-01-01T00:00:00.000-0800"/>
			
			<entry key="dataAccess.type" value="csvRead" /> 
			<entry key="dataAccess.name" value="C:\Program Files (x86)\Jenkins\workspace\Jenkins Git Test\Dataloader\account.csv" /> 
				
			
		</map>
	</property>
	</bean>
</beans>
